examples/__init__.py
examples/dqn.py
examples/hello_world.py
examples/manual_play.py
examples/ppo.py
examples/reinforce.py
examples/tabular_q_learning.py
experiments/__init__.py
experiments/it_tests/__init__.py
experiments/it_tests/run.py
experiments/manual_play/__init__.py
experiments/manual_play/v0/__init__.py
experiments/manual_play/v0/maximal_attack/__init__.py
experiments/manual_play/v0/maximal_attack/maximal_vs_manual/__init__.py
experiments/manual_play/v0/maximal_attack/maximal_vs_manual/run.py
experiments/manual_play/v0/minimal_defense/__init__.py
experiments/manual_play/v0/minimal_defense/manual_vs_minimal_defense/__init__.py
experiments/manual_play/v0/minimal_defense/manual_vs_minimal_defense/run.py
experiments/manual_play/v0/random_attack/__init__.py
experiments/manual_play/v0/random_attack/random_vs_manual/__init__.py
experiments/manual_play/v0/random_attack/random_vs_manual/run.py
experiments/manual_play/v0/random_defense/__init__.py
experiments/manual_play/v0/random_defense/manual_vs_random/__init__.py
experiments/manual_play/v0/random_defense/manual_vs_random/run.py
experiments/manual_play/v1/__init__.py
experiments/manual_play/v1/maximal_attack/__init__.py
experiments/manual_play/v1/maximal_attack/maximal_vs_manual/__init__.py
experiments/manual_play/v1/maximal_attack/maximal_vs_manual/run.py
experiments/manual_play/v1/minimal_defense/__init__.py
experiments/manual_play/v1/minimal_defense/manual_vs_random/__init__.py
experiments/manual_play/v1/minimal_defense/manual_vs_random/run.py
experiments/manual_play/v1/random_attack/__init__.py
experiments/manual_play/v1/random_attack/random_vs_manual/__init__.py
experiments/manual_play/v1/random_attack/random_vs_manual/run.py
experiments/manual_play/v1/random_defense/__init__.py
experiments/manual_play/v1/random_defense/manual_vs_random/__init__.py
experiments/manual_play/v1/random_defense/manual_vs_random/run.py
experiments/manual_play/v11/__init__.py
experiments/manual_play/v11/minimal_defense/__init__.py
gym_idsgame-1.0.12.dist-info/LICENSE.md
gym_idsgame-1.0.12.dist-info/METADATA
gym_idsgame-1.0.12.dist-info/WHEEL
gym_idsgame-1.0.12.dist-info/top_level.txt
gym_idsgame-1.0.12.dist-info/RECORD
